{"HN":[{"url":"https://news.ycombinator.com/item?id=11862476","title":"Being sued, in East Texas, for using the Google Play Store [video]","score":"1363"},{"url":"https://news.ycombinator.com/item?id=11862582","title":"Police use new device to seize money in bank accounts or on prepaid cards","score":"552"},{"url":"https://news.ycombinator.com/item?id=11866868","title":"Why I turned down $500K and shut down my startup","score":"473"},{"url":"https://news.ycombinator.com/item?id=11862217","title":"Typosquatting programming language package managers","score":"456"},{"url":"https://news.ycombinator.com/item?id=11864211","title":"How the Windows Subsystem for Linux Redirects Syscalls","score":"332"},{"url":"https://news.ycombinator.com/item?id=11863738","title":"All the best advice we could find on how to get a job","score":"321"},{"url":"https://news.ycombinator.com/item?id=11866987","title":"Microsoft Edge WebGL engine open-sourced","score":"311"},{"url":"https://news.ycombinator.com/item?id=11864776","title":"How Two Seattle-Area Brothers Made Dwarf Fortress","score":"270"},{"url":"https://news.ycombinator.com/item?id=11867672","title":"Passwords for 32M Twitter accounts may have been hacked and leaked","score":"223"},{"url":"https://news.ycombinator.com/item?id=11867751","title":"Elite for Emacs","score":"201"}],"reddit":[{"url":"https://www.reddit.com/r/programming/comments/4n60mp/taking_over_17000_hosts_by_typosquatting_package/","title":"Taking over 17000 hosts by typosquatting package managers like PyPi or npmjs.com"},{"url":"https://www.reddit.com/r/programming/comments/4n7pqx/in_84_tom_duff_posted_a_disgusting_piece_of_c/","title":"In '84, Tom Duff posted a disgusting piece of C code to Usenet and named it after himself"},{"url":"https://www.reddit.com/r/programming/comments/4n8mre/the_app_boom_is_over/","title":"The app boom is over"},{"url":"https://www.reddit.com/r/programming/comments/4n8thq/microsoft_edge_webgl_renderer_mit_open_sourced/","title":"Microsoft Edge WebGL renderer MIT open sourced"},{"url":"https://www.reddit.com/r/programming/comments/4n77ra/pypy_status_blog_pypy2_v53_released_major/","title":"PyPy Status Blog: PyPy2 v5.3 released - major C-extension support improvements"},{"url":"https://www.reddit.com/r/programming/comments/4n5wp7/using_llvm_on_gpus_to_drive_multibillion_row/","title":"Using LLVM on GPUs to Drive Multi-Billion Row Database Queries"},{"url":"https://www.reddit.com/r/programming/comments/4n65x2/ocaml_mode_in_visual_studio_code_with_debugger/","title":"OCaml Mode in Visual Studio Code with Debugger"},{"url":"https://www.reddit.com/r/programming/comments/4n60r2/how_i_reverseengineered_my_old_8051based_toy/","title":"How I reverse-engineered my old 8051-based toy"},{"url":"https://www.reddit.com/r/programming/comments/4n7qnf/oxygen_os_is_now_open_source/","title":"Oxygen OS is now Open Source!"},{"url":"https://www.reddit.com/r/programming/comments/4naaba/google_deepmind_ai_learns_to_play_montezumas/","title":"Google DeepMind AI learns to play 'Montezuma's Revenge'"}],"medium":[{"title":"Versioning, Licensing, and Sketch 4.0","url":"https://medium.com/p/versioning-licensing-and-sketch-4-0-8ad98783e9ba"},{"title":"The Future of Television","url":"https://medium.com/p/future-of-tv-chuck-klosterman-what-if-were-wrong-46ecb1a5444"},{"title":"Why I turned down $500K, Pissed off my investors, and Shut down my startup","url":"https://medium.com/p/why-i-turned-down-500k-pissed-off-my-investors-and-shut-down-my-startup-2645c4ca1354"},{"title":"Why Do the Poor Make Such Poor Decisions?","url":"https://medium.com/p/why-do-the-poor-make-such-poor-decisions-f05d84c44f1a"},{"title":"How to Reinvent Yourself","url":"https://medium.com/p/how-to-reinvent-yourself-1a8282dde26e"},{"title":"Do You Take Yourself Seriously?","url":"https://medium.com/p/do-you-take-yourself-seriously-704418a5f614"},{"title":"What the Returns of the Hound and the Blackfish Mean for ‘Game of Thrones’","url":"https://medium.com/p/ask-the-maester-game-of-thrones-broken-man-72b51604d7d5"},{"title":"30 Behaviors That Will Make You Unstoppable","url":"https://medium.com/p/30-behaviors-that-will-make-you-unstoppable-31d1d4e4c9c9"},{"title":"The Future is Paved with Broken Glass","url":"https://medium.com/p/the-future-is-paved-with-broken-glass-ccea3d652411"},{"title":"The End of the Router ?","url":"https://medium.com/p/the-end-of-the-router-e4d769aea60f"}],"github":[{"url":"https://github.com/sahat/megaboilerplate","title":"sahat/megaboilerplate:  Handcrafted starter projects, optimized for simplicity and ease of use."},{"url":"https://github.com/FreeCodeCamp/FreeCodeCamp","title":"FreeCodeCamp/FreeCodeCamp: The  open source codebase and curriculum. Learn to code and help nonprofits."},{"url":"https://github.com/git-tips/tips","title":"git-tips/tips: Most commonly used git tips and tricks."},{"url":"https://github.com/joshbuchea/HEAD","title":"joshbuchea/HEAD: A list of everything that could go in the &lt;head&gt; of your document"},{"url":"https://github.com/airbnb/hypernova","title":"airbnb/hypernova: A service for server-side rendering your JavaScript views"},{"url":"https://github.com/wiseio/paratext","title":"wiseio/paratext: A library for reading text files over multiple cores."},{"url":"https://github.com/luruke/barba.js","title":"luruke/barba.js: Create badass, fluid and smooth transition between your website's pages."},{"url":"https://github.com/MicrosoftEdge/WebGL","title":"MicrosoftEdge/WebGL: Microsoft Edge WebGL Implementation"},{"url":"https://github.com/raywenderlich/swift-algorithm-club","title":"raywenderlich/swift-algorithm-club: Algorithms and data structures in Swift, with explanations!"},{"url":"https://github.com/googlecreativelab/anypixel","title":"googlecreativelab/anypixel: A web-friendly way for anyone to build unusual displays"}],"v2ex":[{"url":"https://www.v2ex.com/t/284529","title":"境外 IP 全部无法访问"},{"url":"https://www.v2ex.com/t/284589","title":"今年 820 旗舰 买哪个?"},{"url":"https://www.v2ex.com/t/284510","title":"没玩过《魔兽世界》和《魔兽争霸》去看完电影《魔兽》是一种什么体验？"},{"url":"https://www.v2ex.com/t/284533","title":"湖北电信到美国线路全部挂掉了吗？"},{"url":"https://www.v2ex.com/t/284630","title":"为什么安卓手机屏容易磨花？苹果裸奔都没事？"},{"url":"https://www.v2ex.com/t/284561","title":"作为程序员在厦门工作如何？毕业打算去厦门工作"},{"url":"https://www.v2ex.com/t/284569","title":"20160609 - 中国电信路由问题"},{"url":"https://www.v2ex.com/t/284570","title":"新的 rmbp 没有 esc， vim 怎么玩！"},{"url":"https://www.v2ex.com/t/284508","title":"残酷底层物语:一个视频软件的中国农村"}]}